spoqa_aws_xray_flask_middleware.py
spoqa_aws_xray_flask_middleware-0.1.2.dist-info/LICENSE
spoqa_aws_xray_flask_middleware-0.1.2.dist-info/WHEEL
spoqa_aws_xray_flask_middleware-0.1.2.dist-info/METADATA
spoqa_aws_xray_flask_middleware-0.1.2.dist-info/RECORD
