Metadata-Version: 2.1
Name: spoqa-aws-xray-flask-middleware
Version: 0.1.2
Summary: Spoqa flavoured AWS X-Ray middleware for Flask
Home-page: https://github.com/spoqa/aws-xray-flask-middleware
License: MIT
Author: Spoqa Creators
Author-email: dev@spoqa.com
Maintainer: rusty
Maintainer-email: rusty@spoqa.com
Requires-Python: >=2.7, !=3.0.*, !=3.1.*, !=3.2.*, !=3.3.*, !=3.4.*
Classifier: License :: OSI Approved :: MIT License
Classifier: Programming Language :: Python :: 2
Classifier: Programming Language :: Python :: 2.7
Classifier: Programming Language :: Python :: 3
Classifier: Programming Language :: Python :: 3.5
Classifier: Programming Language :: Python :: 3.6
Classifier: Programming Language :: Python :: 3.7
Classifier: Programming Language :: Python :: 3.8
Requires-Dist: aws-xray-sdk (>=2.6.0,<3.0.0)
Requires-Dist: flask (>=0.10)
Project-URL: Repository, https://github.com/spoqa/aws-xray-flask-middleware
